pathshortener/__init__.py
pathshortener/__main__.py
pathshortener/env_vars.py
pathshortener/registry.py
pathshortener/string_processing.py
pathshortener-0.1.1.dist-info/METADATA
pathshortener-0.1.1.dist-info/WHEEL
pathshortener-0.1.1.dist-info/entry_points.txt
pathshortener-0.1.1.dist-info/top_level.txt
pathshortener-0.1.1.dist-info/RECORD
